{"expireTime":9007200856802874000,"key":"create-remote-file-node-http://localhost:1337/uploads/projects_2_8c84a79928.jpg","val":{"vary":"Origin","strict-transport-security":"max-age=31536000; includeSubDomains","x-frame-options":"SAMEORIGIN","accept-ranges":"bytes","content-length":"522590","last-modified":"Thu, 01 Oct 2020 09:41:13 GMT","cache-control":"max-age=0","content-type":"image/jpeg","x-powered-by":"Strapi <strapi.io>","x-response-time":"1ms","date":"Wed, 07 Oct 2020 09:11:23 GMT","connection":"close"}}